typeitnow/__init__.py
typeitnow/ascii_gen.py
typeitnow/game_over.py
typeitnow/main.py
typeitnow/music.py
typeitnow/sf2_download.py
typeitnow/user_prompt.py
typeitnow/ascii/ascii_characters.py
typeitnow/ascii/words.py
typeitnow/music/type-it.mid
typeitnow-0.1.3.dist-info/METADATA
typeitnow-0.1.3.dist-info/WHEEL
typeitnow-0.1.3.dist-info/entry_points.txt
typeitnow-0.1.3.dist-info/RECORD
