Metadata-Version: 2.4
Name: typeitnow
Version: 0.1.3
Summary: A terminal-based typing game inspired by bop it.
Requires-Python: >=3.13
Requires-Dist: art>=6.5
Requires-Dist: inputimeout>=1.0.4
Requires-Dist: mido>=1.3.3
Requires-Dist: pathlib>=1.0.1
Requires-Dist: platformdirs>=4.5.0
Requires-Dist: pyfluidsynth>=1.3.4
